osm_annotation/__init__.py
osm_annotation/geofabrik_database.py
osm_annotation/semantic_annotation.py
osm_annotation/label_map/osm_label_hierarchy.csv
osm_annotation/label_map/osm_label_hierarchy_clean.csv
osm_annotation-0.1.10.dist-info/LICENSE
osm_annotation-0.1.10.dist-info/METADATA
osm_annotation-0.1.10.dist-info/WHEEL
osm_annotation-0.1.10.dist-info/top_level.txt
osm_annotation-0.1.10.dist-info/RECORD
