Metadata-Version: 2.1
Name: osm_annotation
Version: 0.1.10
Summary: An easy-to-use Python package that annotate location data with semantic labels from OpenStreetMap
Home-page: https://bitbucket.org/mhealthresearchgroup/osm_annotation/src/main/
Author: Jixin Li
Author-email: li.jix@northeastern.edu
Project-URL: Bug Tracker, https://bitbucket.org/mhealthresearchgroup/osm_annotation/issues?status=new&status=open
Classifier: Programming Language :: Python :: 3
Classifier: License :: OSI Approved :: MIT License
Classifier: Operating System :: OS Independent
Requires-Python: >=3.7
License-File: LICENSE
